ukosnik/__init__.py
ukosnik/__main__.py
ukosnik/docent.py
ukosnik/document.py
ukosnik/http.py
ukosnik-0.1.3.dist-info/LICENSE
ukosnik-0.1.3.dist-info/METADATA
ukosnik-0.1.3.dist-info/WHEEL
ukosnik-0.1.3.dist-info/entry_points.txt
ukosnik-0.1.3.dist-info/top_level.txt
ukosnik-0.1.3.dist-info/RECORD
