Metadata-Version: 2.1
Name: ukosnik
Version: 0.1.3
Summary: Manage Discord Slash Commands
Home-page: https://github.com/Unoqwy/ukosnik
Author: Unoqwy
License: MIT
Project-URL: Bug Tracker, https://github.com/Unoqwy/ukosnik/issues
Keywords: discord
Platform: UNKNOWN
Classifier: Development Status :: 3 - Alpha
Classifier: Natural Language :: English
Classifier: License :: OSI Approved :: MIT License
Classifier: Operating System :: OS Independent
Classifier: Programming Language :: Python :: 3
Requires-Python: >=3.6
Requires-Dist: PyYAML (<=6,>=5)
Requires-Dist: requests (<=3,>=2.25)
Requires-Dist: typing-extensions (==3.10.0.0)
Requires-Dist: dataclasses (==0.8) ; python_version < "3.7"
